<?xml version="1.0" encoding="UTF-8" standalone="yes"?>
<olimpiad>
    <id>1</id>
    <name>Biology</name>
    <task>
        <question>1</question>
        <description>First task for begginer</description>
        <olimpId>1</olimpId>
    </task>
    <task>
        <question>2</question>
        <description>Second task for begginer</description>
        <olimpId>1</olimpId>
    </task>
    <task>
        <question>3</question>
        <description>Third task for begginer</description>
        <olimpId>1</olimpId>
    </task>
    <task>
        <question>4</question>
        <description>Test task number four</description>
        <olimpId>1</olimpId>
    </task>
    <task>
        <question>5</question>
        <description>One more task # 5</description>
        <olimpId>1</olimpId>
    </task>
</olimpiad>
